[
    {
        "name": "Star Sports 1",
        "id": "star1in",
        "logo": "https://cdn.jsdelivr.net/gh/HelloPeopleTv4you/tv-logo@refs/heads/main/crichd2-runded/16-by-xfireflix.png",
        "link": "https://off1.gogohaalmal.com:1686/hls/star1in.m3u8?md5=bd_P1yDSjP6y58q2GCSiSw&expires=1746495172",
        "referer": "https://stylisheleg4nt.com",
        "origin": "https://stylisheleg4nt.com"
    },
    {
        "name": "Star Sports 1 Hindi",
        "id": "starhindi",
        "logo": "https://cdn.jsdelivr.net/gh/HelloPeopleTv4you/tv-logo@refs/heads/main/crichd2-runded/1-by-xfireflix.png",
        "link": "https://m5.merichunidya.com:999/hls/starhindi.m3u8?md5=z-ztjRQpst-WAm7VuDRTSg&expires=1746495172",
        "referer": "https://stylisheleg4nt.com",
        "origin": "https://stylisheleg4nt.com"
    },
    {
        "name": "PTV Sports",
        "id": "ptvpk",
        "logo": "https://cdn.jsdelivr.net/gh/HelloPeopleTv4you/tv-logo@refs/heads/main/crichd2-runded/20-by-xfireflix.png",
        "link": "https://m6.merichunidya.com:999/hls/ptvpk.m3u8?md5=zY4HmIrmNS4D85Re_HVt1A&expires=1746495173",
        "referer": "https://stylisheleg4nt.com",
        "origin": "https://stylisheleg4nt.com"
    },
    {
        "name": "Willow HD",
        "id": "willowusa",
        "logo": "https://cdn.jsdelivr.net/gh/HelloPeopleTv4you/tv-logo@refs/heads/main/crichd2-runded/38-by-xfireflix.png",
        "link": "https://off1.gogohaalmal.com:1686/hls/willowusa.m3u8?md5=DsluGvOJIx-8-OAonfdgMg&expires=1746495173",
        "referer": "https://stylisheleg4nt.com",
        "origin": "https://stylisheleg4nt.com"
    },
    {
        "name": "Willow HD 2",
        "id": "willowextra",
        "logo": "https://cdn.jsdelivr.net/gh/HelloPeopleTv4you/tv-logo@refs/heads/main/crichd2-runded/8-by-xfireflix.png",
        "link": "https://off1.gogohaalmal.com:1686/hls/willowextra.m3u8?md5=RI1ZxgL3OuuR05UYsGIpKA&expires=1746495173",
        "referer": "https://stylisheleg4nt.com",
        "origin": "https://stylisheleg4nt.com"
    },
    {
        "name": "Ten Sports",
        "id": "tenspk",
        "logo": "https://cdn.jsdelivr.net/gh/HelloPeopleTv4you/tv-logo@refs/heads/main/crichd2-runded/10-by-xfireflix.png",
        "link": "https://off1.gogohaalmal.com:1686/hls/tenspk.m3u8?md5=gVPaieomwZfgM6XMgNZ7MQ&expires=1746495173",
        "referer": "https://stylisheleg4nt.com",
        "origin": "https://stylisheleg4nt.com"
    },
    {
        "name": "A Sports HD",
        "id": "asportshd",
        "logo": "https://cdn.jsdelivr.net/gh/HelloPeopleTv4you/tv-logo@refs/heads/main/crichd2-runded/12-by-xfireflix.png",
        "link": "https://m6.merichunidya.com:999/hls/asportshd.m3u8?md5=ShJI36MAYzpDPAadY3yxog&expires=1746495173",
        "referer": "https://stylisheleg4nt.com",
        "origin": "https://stylisheleg4nt.com"
    },
    {
        "name": "Sky Sports Cricket",
        "id": "skyscric",
        "logo": "https://cdn.jsdelivr.net/gh/HelloPeopleTv4you/tv-logo@refs/heads/main/crichd2-runded/9-by-xfireflix.png",
        "link": "https://m5.merichunidya.com:999/hls/skyscric.m3u8?md5=iZsrta-ru9mYxSIxpffeow&expires=1746495173",
        "referer": "https://stylisheleg4nt.com",
        "origin": "https://stylisheleg4nt.com"
    },
    {
        "name": "Sky Sports Main Event",
        "id": "skysme",
        "logo": "https://cdn.jsdelivr.net/gh/HelloPeopleTv4you/tv-logo@refs/heads/main/crichd2-runded/18-by-xfireflix.png",
        "link": "https://m6.merichunidya.com:999/hls/skysme.m3u8?md5=4OAq2po6hX0iDJNqKervsw&expires=1746495173",
        "referer": "https://stylisheleg4nt.com",
        "origin": "https://stylisheleg4nt.com"
    },
    {
        "name": "TNT 1",
        "logo": "https://cdn.jsdelivr.net/gh/HelloPeopleTv4you/tv-logo@refs/heads/main/crichd2-runded/tnt.png",
        "error": "Token not found or failed to fetch."
    },
    {
        "name": "TNT 2",
        "id": "bbtsp2",
        "logo": "https://cdn.jsdelivr.net/gh/HelloPeopleTv4you/tv-logo@refs/heads/main/crichd2-runded/tnt.png",
        "link": "https://m6.merichunidya.com:999/hls/bbtsp2.m3u8?md5=MyZw_8sMHXUPJqh_OwS4yQ&expires=1746495173",
        "referer": "https://stylisheleg4nt.com",
        "origin": "https://stylisheleg4nt.com"
    },
    {
        "name": "TNT 3",
        "id": "bbtsp3",
        "logo": "https://cdn.jsdelivr.net/gh/HelloPeopleTv4you/tv-logo@refs/heads/main/crichd2-runded/tnt.png",
        "link": "https://off1.gogohaalmal.com:1686/hls/bbtsp3.m3u8?md5=0ndi_H-KZE68J5XRjbv3_g&expires=1746495173",
        "referer": "https://stylisheleg4nt.com",
        "origin": "https://stylisheleg4nt.com"
    },
    {
        "name": "TNT 4",
        "id": "bbtespn",
        "logo": "https://cdn.jsdelivr.net/gh/HelloPeopleTv4you/tv-logo@refs/heads/main/crichd2-runded/tnt.png",
        "link": "https://off1.gogohaalmal.com:1686/hls/bbtespn.m3u8?md5=dgaLG3CvBdkKDepBVCeG8g&expires=1746495173",
        "referer": "https://stylisheleg4nt.com",
        "origin": "https://stylisheleg4nt.com"
    },
    {
        "name": "Sky Sports 1",
        "id": "sky1nz",
        "logo": "https://cdn.jsdelivr.net/gh/HelloPeopleTv4you/tv-logo@refs/heads/main/crichd2-runded/56-by-xfireflix.png",
        "link": "https://m7.merichunidya.com:999/hls/sky1nz.m3u8?md5=udM5vCJgRUarwCa3zLAcCw&expires=1746495174",
        "referer": "https://stylisheleg4nt.com",
        "origin": "https://stylisheleg4nt.com"
    },
    {
        "name": "Sky Sports 2",
        "id": "sky2nz",
        "logo": "https://cdn.jsdelivr.net/gh/HelloPeopleTv4you/tv-logo@refs/heads/main/crichd2-runded/56-by-xfireflix.png",
        "link": "https://m5.merichunidya.com:999/hls/sky2nz.m3u8?md5=HR4cvJr4FUN1dzPzkHVP7A&expires=1746495174",
        "referer": "https://stylisheleg4nt.com",
        "origin": "https://stylisheleg4nt.com"
    },
    {
        "name": "Sky Sports 3",
        "id": "sky3nz",
        "logo": "https://cdn.jsdelivr.net/gh/HelloPeopleTv4you/tv-logo@refs/heads/main/crichd2-runded/56-by-xfireflix.png",
        "link": "https://m6.merichunidya.com:999/hls/sky3nz.m3u8?md5=4atvUZ9M3pA4OPWoTXeiiQ&expires=1746495174",
        "referer": "https://stylisheleg4nt.com",
        "origin": "https://stylisheleg4nt.com"
    },
    {
        "name": "Sky Sports 4",
        "id": "sky4nz",
        "logo": "https://cdn.jsdelivr.net/gh/HelloPeopleTv4you/tv-logo@refs/heads/main/crichd2-runded/56-by-xfireflix.png",
        "link": "https://m6.merichunidya.com:999/hls/sky4nz.m3u8?md5=sphAI1k6JK1-UEIAa8hpkA&expires=1746495174",
        "referer": "https://stylisheleg4nt.com",
        "origin": "https://stylisheleg4nt.com"
    },
    {
        "name": "Sky Sports 5",
        "id": "sky5nz",
        "logo": "https://cdn.jsdelivr.net/gh/HelloPeopleTv4you/tv-logo@refs/heads/main/crichd2-runded/56-by-xfireflix.png",
        "link": "https://m5.merichunidya.com:999/hls/sky5nz.m3u8?md5=XH1xMnrO9Xk1Q87whZgYmA&expires=1746495174",
        "referer": "https://stylisheleg4nt.com",
        "origin": "https://stylisheleg4nt.com"
    },
    {
        "name": "Sky Sports 6",
        "id": "sky6nz",
        "logo": "https://cdn.jsdelivr.net/gh/HelloPeopleTv4you/tv-logo@refs/heads/main/crichd2-runded/56-by-xfireflix.png",
        "link": "https://m6.merichunidya.com:999/hls/sky6nz.m3u8?md5=HtYvBKIkPmjhD-JzvN4QmQ&expires=1746495174",
        "referer": "https://stylisheleg4nt.com",
        "origin": "https://stylisheleg4nt.com"
    },
    {
        "name": "Sky Sports 7",
        "id": "sky7nz",
        "logo": "https://cdn.jsdelivr.net/gh/HelloPeopleTv4you/tv-logo@refs/heads/main/crichd2-runded/56-by-xfireflix.png",
        "link": "https://m5.merichunidya.com:999/hls/sky7nz.m3u8?md5=gIw-2io6oPAtZUf7sY2p7A&expires=1746495174",
        "referer": "https://stylisheleg4nt.com",
        "origin": "https://stylisheleg4nt.com"
    },
    {
        "name": "Sky Sports 8",
        "id": "sky8nz",
        "logo": "https://cdn.jsdelivr.net/gh/HelloPeopleTv4you/tv-logo@refs/heads/main/crichd2-runded/56-by-xfireflix.png",
        "link": "https://m7.merichunidya.com:999/hls/sky8nz.m3u8?md5=EiWVTApwFyNometDXbSjdQ&expires=1746495174",
        "referer": "https://stylisheleg4nt.com",
        "origin": "https://stylisheleg4nt.com"
    },
    {
        "name": "Sky Sports 9",
        "id": "sky9nz",
        "logo": "https://cdn.jsdelivr.net/gh/HelloPeopleTv4you/tv-logo@refs/heads/main/crichd2-runded/56-by-xfireflix.png",
        "link": "https://off1.gogohaalmal.com:1686/hls/sky9nz.m3u8?md5=kGMOOX5bSrKlGzNIa4958g&expires=1746495174",
        "referer": "https://stylisheleg4nt.com",
        "origin": "https://stylisheleg4nt.com"
    },
    {
        "name": "Sky Cinema",
        "id": "skysme",
        "logo": "https://cdn.jsdelivr.net/gh/HelloPeopleTv4you/tv-logo@refs/heads/main/crichd2-runded/skycinema.png",
        "link": "https://m5.merichunidya.com:999/hls/skysme.m3u8?md5=LcGMA5O67uLr4nxTMswcNQ&expires=1746495175",
        "referer": "https://stylisheleg4nt.com",
        "origin": "https://stylisheleg4nt.com"
    },
    {
        "name": "Sky Sports Action",
        "id": "skysact",
        "logo": "https://cdn.jsdelivr.net/gh/HelloPeopleTv4you/tv-logo@refs/heads/main/crichd2-runded/1745007829332.png",
        "link": "https://m6.merichunidya.com:999/hls/skysact.m3u8?md5=MHz0SsLmT19HTssassQFEg&expires=1746495175",
        "referer": "https://stylisheleg4nt.com",
        "origin": "https://stylisheleg4nt.com"
    },
    {
        "name": "Sky Sports Golf",
        "id": "skysgol",
        "logo": "https://cdn.jsdelivr.net/gh/HelloPeopleTv4you/tv-logo@refs/heads/main/crichd2-runded/1745008055327.png",
        "link": "https://m7.merichunidya.com:999/hls/skysgol.m3u8?md5=l20ZiPmpfIn72dz21pUXyQ&expires=1746495175",
        "referer": "https://stylisheleg4nt.com",
        "origin": "https://stylisheleg4nt.com"
    },
    {
        "name": "Sky Sports Premier League",
        "logo": "https://cdn.jsdelivr.net/gh/HelloPeopleTv4you/tv-logo@refs/heads/main/crichd2-runded/43-by-xfireflix.png",
        "error": "Token not found or failed to fetch."
    },
    {
        "name": "Sky Sports Football",
        "id": "skysfott",
        "logo": "https://cdn.jsdelivr.net/gh/HelloPeopleTv4you/tv-logo@refs/heads/main/crichd2-runded/44-by-xfireflix.png",
        "link": "https://m6.merichunidya.com:999/hls/skysfott.m3u8?md5=Yx2ZfWsBk1I7DVLwbVL5Tg&expires=1746495175",
        "referer": "https://stylisheleg4nt.com",
        "origin": "https://stylisheleg4nt.com"
    },
    {
        "name": "Sky Sports Plus",
        "id": "skysare",
        "logo": "https://cdn.jsdelivr.net/gh/HelloPeopleTv4you/tv-logo@refs/heads/main/crichd2-runded/1745008347584.png",
        "link": "https://m5.merichunidya.com:999/hls/skysare.m3u8?md5=JuONbKbjYi80ysAodHsT8g&expires=1746495175",
        "referer": "https://stylisheleg4nt.com",
        "origin": "https://stylisheleg4nt.com"
    },
    {
        "name": "Sky Sports F1",
        "id": "skysfor1",
        "logo": "https://cdn.jsdelivr.net/gh/HelloPeopleTv4you/tv-logo@refs/heads/main/crichd2-runded/1745008468637.png",
        "link": "https://off1.gogohaalmal.com:1686/hls/skysfor1.m3u8?md5=YyTMRlkIL03Rpn2Q3vG9xA&expires=1746495175",
        "referer": "https://stylisheleg4nt.com",
        "origin": "https://stylisheleg4nt.com"
    },
    {
        "name": "LaLiGA",
        "id": "laligauk",
        "logo": "https://cdn.jsdelivr.net/gh/HelloPeopleTv4you/tv-logo@refs/heads/main/crichd2-runded/19-by-xfireflix.png",
        "link": "https://m7.merichunidya.com:999/hls/laligauk.m3u8?md5=94WZ3eKZz8C7LCWBPxEabg&expires=1746495175",
        "referer": "https://stylisheleg4nt.com",
        "origin": "https://stylisheleg4nt.com"
    },
    {
        "name": "Premier Sports 1",
        "id": "premieruk",
        "logo": "https://cdn.jsdelivr.net/gh/HelloPeopleTv4you/tv-logo@refs/heads/main/crichd2-runded/31-by-xfireflix.png",
        "link": "https://m6.merichunidya.com:999/hls/premieruk.m3u8?md5=cBrE2Sb1xEUEbtQgqZIfgw&expires=1746495175",
        "referer": "https://stylisheleg4nt.com",
        "origin": "https://stylisheleg4nt.com"
    },
    {
        "name": "Premier Sports 2",
        "logo": "https://cdn.jsdelivr.net/gh/HelloPeopleTv4you/tv-logo@refs/heads/main/crichd2-runded/31-by-xfireflix.png",
        "error": "Token not found or failed to fetch."
    },
    {
        "name": "Super Football",
        "logo": "https://cdn.jsdelivr.net/gh/HelloPeopleTv4you/tv-logo@refs/heads/main/crichd2-runded/34-by-xfireflix.png",
        "error": "Token not found or failed to fetch."
    },
    {
        "name": "Super Premier League",
        "id": "superpremier",
        "logo": "https://cdn.jsdelivr.net/gh/HelloPeopleTv4you/tv-logo@refs/heads/main/crichd2-runded/1745008781606.png",
        "link": "https://off1.gogohaalmal.com:1686/hls/superpremier.m3u8?md5=zn5oMwthttuwos2ZRVI0OQ&expires=1746495175",
        "referer": "https://stylisheleg4nt.com",
        "origin": "https://stylisheleg4nt.com"
    },
    {
        "name": "Astro Cricket",
        "id": "fox501",
        "logo": "https://cdn.jsdelivr.net/gh/HelloPeopleTv4you/tv-logo@refs/heads/main/crichd2-runded/1745008895589.png",
        "link": "https://m7.merichunidya.com:999/hls/fox501.m3u8?md5=MdVbvL0EhaGyFWL9r0HIdw&expires=1746495176",
        "referer": "https://stylisheleg4nt.com",
        "origin": "https://stylisheleg4nt.com"
    },
    {
        "name": "ESPN 1",
        "logo": "https://cdn.jsdelivr.net/gh/HelloPeopleTv4you/tv-logo@refs/heads/main/crichd2-runded/17-by-xfireflix.png",
        "error": "Token not found or failed to fetch."
    },
    {
        "name": "ESPN 2",
        "id": "espn2",
        "logo": "https://cdn.jsdelivr.net/gh/HelloPeopleTv4you/tv-logo@refs/heads/main/crichd2-runded/17-by-xfireflix.png",
        "link": "https://m5.merichunidya.com:999/hls/espn2.m3u8?md5=x8MGBFBVFA7i4UOJWguHeg&expires=1746495176",
        "referer": "https://stylisheleg4nt.com",
        "origin": "https://stylisheleg4nt.com"
    },
    {
        "name": "Sky Sports Arena",
        "id": "skysare",
        "logo": "https://cdn.jsdelivr.net/gh/HelloPeopleTv4you/tv-logo@refs/heads/main/crichd2-runded/1745007829327.png",
        "link": "https://off1.gogohaalmal.com:1686/hls/skysare.m3u8?md5=xdELejBKpyVzG-OrnQ2iLw&expires=1746495176",
        "referer": "https://stylisheleg4nt.com",
        "origin": "https://stylisheleg4nt.com"
    },
    {
        "name": "Sky Sports Mix",
        "id": "skysmixx",
        "logo": "https://cdn.jsdelivr.net/gh/HelloPeopleTv4you/tv-logo@refs/heads/main/crichd2-runded/13-by-xfireflix.png",
        "link": "https://off1.gogohaalmal.com:1686/hls/skysmixx.m3u8?md5=sbkh3vtb9V0_dEF8q_BA-g&expires=1746495176",
        "referer": "https://stylisheleg4nt.com",
        "origin": "https://stylisheleg4nt.com"
    },
    {
        "name": "Sky Sports Tennis",
        "id": "skystennis",
        "logo": "https://cdn.jsdelivr.net/gh/HelloPeopleTv4you/tv-logo@refs/heads/main/crichd2-runded/1745009085794.png",
        "link": "https://m5.merichunidya.com:999/hls/skystennis.m3u8?md5=dA-z8gDkq4jwjPghbPlCCw&expires=1746495176",
        "referer": "https://stylisheleg4nt.com",
        "origin": "https://stylisheleg4nt.com"
    },
    {
        "name": "Fox Cricket 501 HD",
        "id": "fox501",
        "logo": "https://cdn.jsdelivr.net/gh/HelloPeopleTv4you/tv-logo@refs/heads/main/crichd2-runded/6-by-xfireflix.png",
        "link": "https://off1.gogohaalmal.com:1686/hls/fox501.m3u8?md5=MdVbvL0EhaGyFWL9r0HIdw&expires=1746495176",
        "referer": "https://stylisheleg4nt.com",
        "origin": "https://stylisheleg4nt.com"
    }
]