[
    {
        "name": "Star Sports 1",
        "id": "star1in",
        "logo": "https://cdn.jsdelivr.net/gh/HelloPeopleTv4you/tv-logo@refs/heads/main/crichd2-runded/16-by-xfireflix.png",
        "link": "https://m1.merichunidya.com:999/hls/star1in.m3u8?md5=bjIahV8msGQpyLnjLf_2UQ&expires=1746901013",
        "referer": "https://stylisheleg4nt.com",
        "origin": "https://stylisheleg4nt.com"
    },
    {
        "name": "Star Sports 1 Hindi",
        "id": "starhindi",
        "logo": "https://cdn.jsdelivr.net/gh/HelloPeopleTv4you/tv-logo@refs/heads/main/crichd2-runded/1-by-xfireflix.png",
        "link": "https://m4.merichunidya.com:999/hls/starhindi.m3u8?md5=DaqupJPkH-qWraps15hPtg&expires=1746901013",
        "referer": "https://stylisheleg4nt.com",
        "origin": "https://stylisheleg4nt.com"
    },
    {
        "name": "PTV Sports",
        "id": "ptvpk",
        "logo": "https://cdn.jsdelivr.net/gh/HelloPeopleTv4you/tv-logo@refs/heads/main/crichd2-runded/20-by-xfireflix.png",
        "link": "https://m1.merichunidya.com:999/hls/ptvpk.m3u8?md5=Yvb8gyncOC5U9kFMiyRsTg&expires=1746901014",
        "referer": "https://stylisheleg4nt.com",
        "origin": "https://stylisheleg4nt.com"
    },
    {
        "name": "Willow HD",
        "id": "willowusa",
        "logo": "https://cdn.jsdelivr.net/gh/HelloPeopleTv4you/tv-logo@refs/heads/main/crichd2-runded/38-by-xfireflix.png",
        "link": "https://m4.merichunidya.com:999/hls/willowusa.m3u8?md5=GYJV1gYz8bHkPOgnX5Utyg&expires=1746901014",
        "referer": "https://stylisheleg4nt.com",
        "origin": "https://stylisheleg4nt.com"
    },
    {
        "name": "Willow HD 2",
        "id": "willowextra",
        "logo": "https://cdn.jsdelivr.net/gh/HelloPeopleTv4you/tv-logo@refs/heads/main/crichd2-runded/8-by-xfireflix.png",
        "link": "https://off1.gogohaalmal.com:1686/hls/willowextra.m3u8?md5=W_I5a7gA_VAz8BuA0VKlJA&expires=1746901014",
        "referer": "https://stylisheleg4nt.com",
        "origin": "https://stylisheleg4nt.com"
    },
    {
        "name": "Ten Sports",
        "id": "tenspk",
        "logo": "https://cdn.jsdelivr.net/gh/HelloPeopleTv4you/tv-logo@refs/heads/main/crichd2-runded/10-by-xfireflix.png",
        "link": "https://m4.merichunidya.com:999/hls/tenspk.m3u8?md5=t24ych9fU9KnzMj2N16HVw&expires=1746901014",
        "referer": "https://stylisheleg4nt.com",
        "origin": "https://stylisheleg4nt.com"
    },
    {
        "name": "A Sports HD",
        "id": "asportshd",
        "logo": "https://cdn.jsdelivr.net/gh/HelloPeopleTv4you/tv-logo@refs/heads/main/crichd2-runded/12-by-xfireflix.png",
        "link": "https://m4.merichunidya.com:999/hls/asportshd.m3u8?md5=A2rGTPXNp_VnXDzjAojseA&expires=1746901015",
        "referer": "https://stylisheleg4nt.com",
        "origin": "https://stylisheleg4nt.com"
    },
    {
        "name": "Sky Sports Cricket",
        "id": "skyscric",
        "logo": "https://cdn.jsdelivr.net/gh/HelloPeopleTv4you/tv-logo@refs/heads/main/crichd2-runded/9-by-xfireflix.png",
        "link": "https://m3.merichunidya.com:999/hls/skyscric.m3u8?md5=hwu8DlrsPR0S_TkbAh4Sxw&expires=1746901015",
        "referer": "https://stylisheleg4nt.com",
        "origin": "https://stylisheleg4nt.com"
    },
    {
        "name": "Sky Sports Main Event",
        "id": "skysme",
        "logo": "https://cdn.jsdelivr.net/gh/HelloPeopleTv4you/tv-logo@refs/heads/main/crichd2-runded/18-by-xfireflix.png",
        "link": "https://m2.merichunidya.com:999/hls/skysme.m3u8?md5=ZOFQIlzoE6A38PgbcgRv_w&expires=1746901015",
        "referer": "https://stylisheleg4nt.com",
        "origin": "https://stylisheleg4nt.com"
    },
    {
        "name": "TNT 1",
        "id": "bbtsp1",
        "logo": "https://cdn.jsdelivr.net/gh/HelloPeopleTv4you/tv-logo@refs/heads/main/crichd2-runded/tnt.png",
        "link": "https://m3.merichunidya.com:999/hls/bbtsp1.m3u8?md5=-C6izSKCSB91LvODhRKLmQ&expires=1746901015",
        "referer": "https://stylisheleg4nt.com",
        "origin": "https://stylisheleg4nt.com"
    },
    {
        "name": "TNT 2",
        "id": "bbtsp2",
        "logo": "https://cdn.jsdelivr.net/gh/HelloPeopleTv4you/tv-logo@refs/heads/main/crichd2-runded/tnt.png",
        "link": "https://m2.merichunidya.com:999/hls/bbtsp2.m3u8?md5=e4wXPBg412WDh_h_bOGv4g&expires=1746901015",
        "referer": "https://stylisheleg4nt.com",
        "origin": "https://stylisheleg4nt.com"
    },
    {
        "name": "TNT 3",
        "id": "bbtsp3",
        "logo": "https://cdn.jsdelivr.net/gh/HelloPeopleTv4you/tv-logo@refs/heads/main/crichd2-runded/tnt.png",
        "link": "https://off1.gogohaalmal.com:1686/hls/bbtsp3.m3u8?md5=TPQoV2azbNH51bSho8TBzQ&expires=1746901016",
        "referer": "https://stylisheleg4nt.com",
        "origin": "https://stylisheleg4nt.com"
    },
    {
        "name": "TNT 4",
        "id": "bbtespn",
        "logo": "https://cdn.jsdelivr.net/gh/HelloPeopleTv4you/tv-logo@refs/heads/main/crichd2-runded/tnt.png",
        "link": "https://m1.merichunidya.com:999/hls/bbtespn.m3u8?md5=xAAdeETG7c7Xd_9-nE5Sgw&expires=1746901016",
        "referer": "https://stylisheleg4nt.com",
        "origin": "https://stylisheleg4nt.com"
    },
    {
        "name": "Sky Sports 1",
        "id": "sky1nz",
        "logo": "https://cdn.jsdelivr.net/gh/HelloPeopleTv4you/tv-logo@refs/heads/main/crichd2-runded/56-by-xfireflix.png",
        "link": "https://m4.merichunidya.com:999/hls/sky1nz.m3u8?md5=RM0R7Bg6WANJZHbeoMxaCw&expires=1746901016",
        "referer": "https://stylisheleg4nt.com",
        "origin": "https://stylisheleg4nt.com"
    },
    {
        "name": "Sky Sports 2",
        "id": "sky2nz",
        "logo": "https://cdn.jsdelivr.net/gh/HelloPeopleTv4you/tv-logo@refs/heads/main/crichd2-runded/56-by-xfireflix.png",
        "link": "https://off1.gogohaalmal.com:1686/hls/sky2nz.m3u8?md5=z27CA0UnhdU__IhV2G8KFw&expires=1746901016",
        "referer": "https://stylisheleg4nt.com",
        "origin": "https://stylisheleg4nt.com"
    },
    {
        "name": "Sky Sports 3",
        "id": "sky3nz",
        "logo": "https://cdn.jsdelivr.net/gh/HelloPeopleTv4you/tv-logo@refs/heads/main/crichd2-runded/56-by-xfireflix.png",
        "link": "https://m2.merichunidya.com:999/hls/sky3nz.m3u8?md5=ewwcLCkUNHKgw0x5O3rXrA&expires=1746901016",
        "referer": "https://stylisheleg4nt.com",
        "origin": "https://stylisheleg4nt.com"
    },
    {
        "name": "Sky Sports 4",
        "id": "sky4nz",
        "logo": "https://cdn.jsdelivr.net/gh/HelloPeopleTv4you/tv-logo@refs/heads/main/crichd2-runded/56-by-xfireflix.png",
        "link": "https://m4.merichunidya.com:999/hls/sky4nz.m3u8?md5=OMOAOizDqJsyKllInntmeg&expires=1746901017",
        "referer": "https://stylisheleg4nt.com",
        "origin": "https://stylisheleg4nt.com"
    },
    {
        "name": "Sky Sports 5",
        "id": "sky5nz",
        "logo": "https://cdn.jsdelivr.net/gh/HelloPeopleTv4you/tv-logo@refs/heads/main/crichd2-runded/56-by-xfireflix.png",
        "link": "https://m1.merichunidya.com:999/hls/sky5nz.m3u8?md5=bBswEMkQ-z75I87DuTB1hQ&expires=1746901017",
        "referer": "https://stylisheleg4nt.com",
        "origin": "https://stylisheleg4nt.com"
    },
    {
        "name": "Sky Sports 6",
        "id": "sky6nz",
        "logo": "https://cdn.jsdelivr.net/gh/HelloPeopleTv4you/tv-logo@refs/heads/main/crichd2-runded/56-by-xfireflix.png",
        "link": "https://m2.merichunidya.com:999/hls/sky6nz.m3u8?md5=cmFHiQz_QHKsFsUcf766uQ&expires=1746901017",
        "referer": "https://stylisheleg4nt.com",
        "origin": "https://stylisheleg4nt.com"
    },
    {
        "name": "Sky Sports 7",
        "id": "sky7nz",
        "logo": "https://cdn.jsdelivr.net/gh/HelloPeopleTv4you/tv-logo@refs/heads/main/crichd2-runded/56-by-xfireflix.png",
        "link": "https://m3.merichunidya.com:999/hls/sky7nz.m3u8?md5=v0p5hbhEJs7fh7Akh_8iNQ&expires=1746901017",
        "referer": "https://stylisheleg4nt.com",
        "origin": "https://stylisheleg4nt.com"
    },
    {
        "name": "Sky Sports 8",
        "id": "sky8nz",
        "logo": "https://cdn.jsdelivr.net/gh/HelloPeopleTv4you/tv-logo@refs/heads/main/crichd2-runded/56-by-xfireflix.png",
        "link": "https://m1.merichunidya.com:999/hls/sky8nz.m3u8?md5=ZTpNMW6o7uVwWpNn3VdJAw&expires=1746901017",
        "referer": "https://stylisheleg4nt.com",
        "origin": "https://stylisheleg4nt.com"
    },
    {
        "name": "Sky Sports 9",
        "id": "sky9nz",
        "logo": "https://cdn.jsdelivr.net/gh/HelloPeopleTv4you/tv-logo@refs/heads/main/crichd2-runded/56-by-xfireflix.png",
        "link": "https://m1.merichunidya.com:999/hls/sky9nz.m3u8?md5=WLCI6HFViN2UG13qo7ZMcQ&expires=1746901018",
        "referer": "https://stylisheleg4nt.com",
        "origin": "https://stylisheleg4nt.com"
    },
    {
        "name": "Sky Cinema",
        "id": "skysme",
        "logo": "https://cdn.jsdelivr.net/gh/HelloPeopleTv4you/tv-logo@refs/heads/main/crichd2-runded/skycinema.png",
        "link": "https://m4.merichunidya.com:999/hls/skysme.m3u8?md5=3bvTdJRdgCgoaSTAS6LV9Q&expires=1746901018",
        "referer": "https://stylisheleg4nt.com",
        "origin": "https://stylisheleg4nt.com"
    },
    {
        "name": "Sky Sports Action",
        "id": "skysact",
        "logo": "https://cdn.jsdelivr.net/gh/HelloPeopleTv4you/tv-logo@refs/heads/main/crichd2-runded/1745007829332.png",
        "link": "https://m3.merichunidya.com:999/hls/skysact.m3u8?md5=Z8zhOk0wZvwJwgJENw1Krg&expires=1746901018",
        "referer": "https://stylisheleg4nt.com",
        "origin": "https://stylisheleg4nt.com"
    },
    {
        "name": "Sky Sports Golf",
        "id": "skysgol",
        "logo": "https://cdn.jsdelivr.net/gh/HelloPeopleTv4you/tv-logo@refs/heads/main/crichd2-runded/1745008055327.png",
        "link": "https://off1.gogohaalmal.com:1686/hls/skysgol.m3u8?md5=5AZgmUitrI9iUvqiRm4GPw&expires=1746901018",
        "referer": "https://stylisheleg4nt.com",
        "origin": "https://stylisheleg4nt.com"
    },
    {
        "name": "Sky Sports Premier League",
        "id": "skysprem",
        "logo": "https://cdn.jsdelivr.net/gh/HelloPeopleTv4you/tv-logo@refs/heads/main/crichd2-runded/43-by-xfireflix.png",
        "link": "https://off1.gogohaalmal.com:1686/hls/skysprem.m3u8?md5=_UUYyev4yFsslJCFqV1rJw&expires=1746901018",
        "referer": "https://stylisheleg4nt.com",
        "origin": "https://stylisheleg4nt.com"
    },
    {
        "name": "Sky Sports Football",
        "id": "skysfott",
        "logo": "https://cdn.jsdelivr.net/gh/HelloPeopleTv4you/tv-logo@refs/heads/main/crichd2-runded/44-by-xfireflix.png",
        "link": "https://m2.merichunidya.com:999/hls/skysfott.m3u8?md5=Dk8kWz8SgEEhK5UquSVqPg&expires=1746901019",
        "referer": "https://stylisheleg4nt.com",
        "origin": "https://stylisheleg4nt.com"
    },
    {
        "name": "Sky Sports Plus",
        "logo": "https://cdn.jsdelivr.net/gh/HelloPeopleTv4you/tv-logo@refs/heads/main/crichd2-runded/1745008347584.png",
        "error": "Token not found or failed to fetch."
    },
    {
        "name": "Sky Sports F1",
        "id": "skysfor1",
        "logo": "https://cdn.jsdelivr.net/gh/HelloPeopleTv4you/tv-logo@refs/heads/main/crichd2-runded/1745008468637.png",
        "link": "https://m3.merichunidya.com:999/hls/skysfor1.m3u8?md5=lzqqaRPGpCytV7jD7lTd6g&expires=1746901019",
        "referer": "https://stylisheleg4nt.com",
        "origin": "https://stylisheleg4nt.com"
    },
    {
        "name": "LaLiGA",
        "id": "laligauk",
        "logo": "https://cdn.jsdelivr.net/gh/HelloPeopleTv4you/tv-logo@refs/heads/main/crichd2-runded/19-by-xfireflix.png",
        "link": "https://off1.gogohaalmal.com:1686/hls/laligauk.m3u8?md5=mfqVS6aEp69ifYs3drrPPw&expires=1746901019",
        "referer": "https://stylisheleg4nt.com",
        "origin": "https://stylisheleg4nt.com"
    },
    {
        "name": "Premier Sports 1",
        "id": "premieruk",
        "logo": "https://cdn.jsdelivr.net/gh/HelloPeopleTv4you/tv-logo@refs/heads/main/crichd2-runded/31-by-xfireflix.png",
        "link": "https://m2.merichunidya.com:999/hls/premieruk.m3u8?md5=vTiWtC5uBaFiKXvIv1Z2RQ&expires=1746901019",
        "referer": "https://stylisheleg4nt.com",
        "origin": "https://stylisheleg4nt.com"
    },
    {
        "name": "Premier Sports 2",
        "id": "hdchnl2",
        "logo": "https://cdn.jsdelivr.net/gh/HelloPeopleTv4you/tv-logo@refs/heads/main/crichd2-runded/31-by-xfireflix.png",
        "link": "https://m1.merichunidya.com:999/hls/hdchnl2.m3u8?md5=7Y9SQSfpWhlIRgDgBmMc4g&expires=1746901019",
        "referer": "https://stylisheleg4nt.com",
        "origin": "https://stylisheleg4nt.com"
    },
    {
        "name": "Super Football",
        "logo": "https://cdn.jsdelivr.net/gh/HelloPeopleTv4you/tv-logo@refs/heads/main/crichd2-runded/34-by-xfireflix.png",
        "error": "Token not found or failed to fetch."
    },
    {
        "name": "Super Premier League",
        "id": "superpremier",
        "logo": "https://cdn.jsdelivr.net/gh/HelloPeopleTv4you/tv-logo@refs/heads/main/crichd2-runded/1745008781606.png",
        "link": "https://m1.merichunidya.com:999/hls/superpremier.m3u8?md5=SNXPA8zzTqSHIQ6waA4s-Q&expires=1746901020",
        "referer": "https://stylisheleg4nt.com",
        "origin": "https://stylisheleg4nt.com"
    },
    {
        "name": "Astro Cricket",
        "id": "fox501",
        "logo": "https://cdn.jsdelivr.net/gh/HelloPeopleTv4you/tv-logo@refs/heads/main/crichd2-runded/1745008895589.png",
        "link": "https://m3.merichunidya.com:999/hls/fox501.m3u8?md5=nA4p-_h9ZG1l8r4ZlOMVhA&expires=1746901020",
        "referer": "https://stylisheleg4nt.com",
        "origin": "https://stylisheleg4nt.com"
    },
    {
        "name": "ESPN 1",
        "id": "espnusa",
        "logo": "https://cdn.jsdelivr.net/gh/HelloPeopleTv4you/tv-logo@refs/heads/main/crichd2-runded/17-by-xfireflix.png",
        "link": "https://off1.gogohaalmal.com:1686/hls/espnusa.m3u8?md5=5cKUQbR9xE7pwtmnTkdjqw&expires=1746901020",
        "referer": "https://stylisheleg4nt.com",
        "origin": "https://stylisheleg4nt.com"
    },
    {
        "name": "ESPN 2",
        "id": "espn2",
        "logo": "https://cdn.jsdelivr.net/gh/HelloPeopleTv4you/tv-logo@refs/heads/main/crichd2-runded/17-by-xfireflix.png",
        "link": "https://m1.merichunidya.com:999/hls/espn2.m3u8?md5=x9GIxfHg14vBLEpFVb-BbA&expires=1746901020",
        "referer": "https://stylisheleg4nt.com",
        "origin": "https://stylisheleg4nt.com"
    },
    {
        "name": "Sky Sports Arena",
        "logo": "https://cdn.jsdelivr.net/gh/HelloPeopleTv4you/tv-logo@refs/heads/main/crichd2-runded/1745007829327.png",
        "error": "Token not found or failed to fetch."
    },
    {
        "name": "Sky Sports Mix",
        "logo": "https://cdn.jsdelivr.net/gh/HelloPeopleTv4you/tv-logo@refs/heads/main/crichd2-runded/13-by-xfireflix.png",
        "error": "Token not found or failed to fetch."
    },
    {
        "name": "Sky Sports Tennis",
        "id": "skystennis",
        "logo": "https://cdn.jsdelivr.net/gh/HelloPeopleTv4you/tv-logo@refs/heads/main/crichd2-runded/1745009085794.png",
        "link": "https://m2.merichunidya.com:999/hls/skystennis.m3u8?md5=lXQl_nAiLlq2ocuA1V_R8Q&expires=1746901021",
        "referer": "https://stylisheleg4nt.com",
        "origin": "https://stylisheleg4nt.com"
    },
    {
        "name": "Fox Cricket 501 HD",
        "id": "fox501",
        "logo": "https://cdn.jsdelivr.net/gh/HelloPeopleTv4you/tv-logo@refs/heads/main/crichd2-runded/6-by-xfireflix.png",
        "link": "https://off1.gogohaalmal.com:1686/hls/fox501.m3u8?md5=h3h2zbO9XQ9eXT1nVZorCA&expires=1746901021",
        "referer": "https://stylisheleg4nt.com",
        "origin": "https://stylisheleg4nt.com"
    }
]