[
    {
        "name": "Star Sports 1",
        "logo": "https://cdn.jsdelivr.net/gh/HelloPeopleTv4you/tv-logo@refs/heads/main/crichd2-runded/16-by-xfireflix.png",
        "url": "https://pol6.dunyapurkaraja.com:999/hls/star1in.m3u8?md5=FrjRDcpUFgvfRCaxBCESBg&expires=1745054028",
        "referer": "https://stylisheleg4nt.com",
        "origin": "https://stylisheleg4nt.com"
    },
    {
        "name": "Star Sports 1 Hindi",
        "logo": "https://cdn.jsdelivr.net/gh/HelloPeopleTv4you/tv-logo@refs/heads/main/crichd2-runded/1-by-xfireflix.png",
        "url": "https://pol6.dunyapurkaraja.com:999/hls/starhindi.m3u8?md5=8kCeSzlvkDfcsVQLH9ZU3w&expires=1745054028",
        "referer": "https://stylisheleg4nt.com",
        "origin": "https://stylisheleg4nt.com"
    },
    {
        "name": "PTV Sports",
        "logo": "https://cdn.jsdelivr.net/gh/HelloPeopleTv4you/tv-logo@refs/heads/main/crichd2-runded/20-by-xfireflix.png",
        "url": "https://pol6.dunyapurkaraja.com:999/hls/ptvpk.m3u8?md5=PvE_jzpuQSRdc80cNL0bKA&expires=1745054028",
        "referer": "https://stylisheleg4nt.com",
        "origin": "https://stylisheleg4nt.com"
    },
    {
        "name": "Willow HD",
        "logo": "https://cdn.jsdelivr.net/gh/HelloPeopleTv4you/tv-logo@refs/heads/main/crichd2-runded/38-by-xfireflix.png",
        "url": "https://pol5.dunyapurkaraja.com:999/hls/willowusa.m3u8?md5=VQAt1R0auYP14jNTuQ4UhQ&expires=1745054029",
        "referer": "https://stylisheleg4nt.com",
        "origin": "https://stylisheleg4nt.com"
    },
    {
        "name": "Willow HD 2",
        "logo": "https://cdn.jsdelivr.net/gh/HelloPeopleTv4you/tv-logo@refs/heads/main/crichd2-runded/8-by-xfireflix.png",
        "url": "https://pol6.dunyapurkaraja.com:999/hls/willowextra.m3u8?md5=-HWqUdjbMxUGgTXltUul6g&expires=1745054029",
        "referer": "https://stylisheleg4nt.com",
        "origin": "https://stylisheleg4nt.com"
    },
    {
        "name": "Ten Sports",
        "logo": "https://cdn.jsdelivr.net/gh/HelloPeopleTv4you/tv-logo@refs/heads/main/crichd2-runded/10-by-xfireflix.png",
        "url": "https://pol6.dunyapurkaraja.com:999/hls/tenspk.m3u8?md5=ARS04ZJXjWY2acjqo897tA&expires=1745054029",
        "referer": "https://stylisheleg4nt.com",
        "origin": "https://stylisheleg4nt.com"
    },
    {
        "name": "A Sports HD",
        "logo": "https://cdn.jsdelivr.net/gh/HelloPeopleTv4you/tv-logo@refs/heads/main/crichd2-runded/12-by-xfireflix.png",
        "url": "https://pol6.dunyapurkaraja.com:999/hls/asportshd.m3u8?md5=I12LRIWq3PYggl3PX9UIrg&expires=1745054029",
        "referer": "https://stylisheleg4nt.com",
        "origin": "https://stylisheleg4nt.com"
    },
    {
        "name": "Sky Sports Cricket",
        "logo": "https://cdn.jsdelivr.net/gh/HelloPeopleTv4you/tv-logo@refs/heads/main/crichd2-runded/9-by-xfireflix.png",
        "url": "https://pol6.dunyapurkaraja.com:999/hls/skyscric.m3u8?md5=mME5Z3PxfxNbuKal1ldyUw&expires=1745054029",
        "referer": "https://stylisheleg4nt.com",
        "origin": "https://stylisheleg4nt.com"
    },
    {
        "name": "Sky Sports Main Event",
        "logo": "https://cdn.jsdelivr.net/gh/HelloPeopleTv4you/tv-logo@refs/heads/main/crichd2-runded/18-by-xfireflix.png",
        "url": "https://pol5.dunyapurkaraja.com:999/hls/skysme.m3u8?md5=Ov8Wl9fQNShTFd52PD4xbQ&expires=1745054029",
        "referer": "https://stylisheleg4nt.com",
        "origin": "https://stylisheleg4nt.com"
    },
    {
        "name": "TNT 1",
        "logo": "https://cdn.jsdelivr.net/gh/HelloPeopleTv4you/tv-logo@refs/heads/main/crichd2-runded/tnt.png",
        "url": "https://pol6.dunyapurkaraja.com:999/hls/bbtsp1.m3u8?md5=XRdVOpOUTHK4t0qgQSf17A&expires=1745054029",
        "referer": "https://stylisheleg4nt.com",
        "origin": "https://stylisheleg4nt.com"
    },
    {
        "name": "TNT 2",
        "logo": "https://cdn.jsdelivr.net/gh/HelloPeopleTv4you/tv-logo@refs/heads/main/crichd2-runded/tnt.png",
        "url": "https://pol7.dunyapurkaraja.com:999/hls/bbtsp2.m3u8?md5=2tbgEKXsVopM5S7o5lhz7w&expires=1745054029",
        "referer": "https://stylisheleg4nt.com",
        "origin": "https://stylisheleg4nt.com"
    },
    {
        "name": "TNT 3",
        "logo": "https://cdn.jsdelivr.net/gh/HelloPeopleTv4you/tv-logo@refs/heads/main/crichd2-runded/tnt.png",
        "url": "https://pol6.dunyapurkaraja.com:999/hls/bbtsp3.m3u8?md5=g2I3-N3r60fZaj0n9v4oWg&expires=1745054029",
        "referer": "https://stylisheleg4nt.com",
        "origin": "https://stylisheleg4nt.com"
    },
    {
        "name": "TNT 4",
        "logo": "https://cdn.jsdelivr.net/gh/HelloPeopleTv4you/tv-logo@refs/heads/main/crichd2-runded/tnt.png",
        "url": "https://pol7.dunyapurkaraja.com:999/hls/bbtespn.m3u8?md5=8gNm55kYl-vhh4UprSl52Q&expires=1745054030",
        "referer": "https://stylisheleg4nt.com",
        "origin": "https://stylisheleg4nt.com"
    },
    {
        "name": "Sky Sports 1",
        "logo": "https://cdn.jsdelivr.net/gh/HelloPeopleTv4you/tv-logo@refs/heads/main/crichd2-runded/56-by-xfireflix.png",
        "url": "https://pol6.dunyapurkaraja.com:999/hls/sky1nz.m3u8?md5=WaVUUnEJuCknqdxaxli3Pw&expires=1745054030",
        "referer": "https://stylisheleg4nt.com",
        "origin": "https://stylisheleg4nt.com"
    },
    {
        "name": "Sky Sports 2",
        "logo": "https://cdn.jsdelivr.net/gh/HelloPeopleTv4you/tv-logo@refs/heads/main/crichd2-runded/56-by-xfireflix.png",
        "url": "https://pol5.dunyapurkaraja.com:999/hls/sky2nz.m3u8?md5=p_HMiZm-_1Au7-bq0b07Jw&expires=1745054030",
        "referer": "https://stylisheleg4nt.com",
        "origin": "https://stylisheleg4nt.com"
    },
    {
        "name": "Sky Sports 3",
        "logo": "https://cdn.jsdelivr.net/gh/HelloPeopleTv4you/tv-logo@refs/heads/main/crichd2-runded/56-by-xfireflix.png",
        "url": "https://pol6.dunyapurkaraja.com:999/hls/sky3nz.m3u8?md5=k4jUdomniaWbBlEZsiQPbw&expires=1745054030",
        "referer": "https://stylisheleg4nt.com",
        "origin": "https://stylisheleg4nt.com"
    },
    {
        "name": "Sky Sports 4",
        "logo": "https://cdn.jsdelivr.net/gh/HelloPeopleTv4you/tv-logo@refs/heads/main/crichd2-runded/56-by-xfireflix.png",
        "url": "https://pol6.dunyapurkaraja.com:999/hls/sky4nz.m3u8?md5=kBqyuZ5dUDNmSBEsfpsjsw&expires=1745054030",
        "referer": "https://stylisheleg4nt.com",
        "origin": "https://stylisheleg4nt.com"
    },
    {
        "name": "Sky Sports 5",
        "logo": "https://cdn.jsdelivr.net/gh/HelloPeopleTv4you/tv-logo@refs/heads/main/crichd2-runded/56-by-xfireflix.png",
        "url": "https://pol7.dunyapurkaraja.com:999/hls/sky5nz.m3u8?md5=mg2Zm-IFUwCq4xnkFTJ9sQ&expires=1745054030",
        "referer": "https://stylisheleg4nt.com",
        "origin": "https://stylisheleg4nt.com"
    },
    {
        "name": "Sky Sports 6",
        "logo": "https://cdn.jsdelivr.net/gh/HelloPeopleTv4you/tv-logo@refs/heads/main/crichd2-runded/56-by-xfireflix.png",
        "url": "https://pol5.dunyapurkaraja.com:999/hls/sky6nz.m3u8?md5=W0MP8iDArquM23n-X-jvZA&expires=1745054030",
        "referer": "https://stylisheleg4nt.com",
        "origin": "https://stylisheleg4nt.com"
    },
    {
        "name": "Sky Sports 7",
        "logo": "https://cdn.jsdelivr.net/gh/HelloPeopleTv4you/tv-logo@refs/heads/main/crichd2-runded/56-by-xfireflix.png",
        "url": "https://pol7.dunyapurkaraja.com:999/hls/sky7nz.m3u8?md5=o_e0wrfX6pPLWBkcxByAHg&expires=1745054030",
        "referer": "https://stylisheleg4nt.com",
        "origin": "https://stylisheleg4nt.com"
    },
    {
        "name": "Sky Sports 8",
        "logo": "https://cdn.jsdelivr.net/gh/HelloPeopleTv4you/tv-logo@refs/heads/main/crichd2-runded/56-by-xfireflix.png",
        "url": "https://pol7.dunyapurkaraja.com:999/hls/sky8nz.m3u8?md5=_Az8jbKzqSKUFpqbGFiedg&expires=1745054030",
        "referer": "https://stylisheleg4nt.com",
        "origin": "https://stylisheleg4nt.com"
    },
    {
        "name": "Sky Sports 9",
        "logo": "https://cdn.jsdelivr.net/gh/HelloPeopleTv4you/tv-logo@refs/heads/main/crichd2-runded/56-by-xfireflix.png",
        "url": "https://pol5.dunyapurkaraja.com:999/hls/sky9nz.m3u8?md5=j9qixqrdV9h9fObUZeoG9Q&expires=1745054030",
        "referer": "https://stylisheleg4nt.com",
        "origin": "https://stylisheleg4nt.com"
    },
    {
        "name": "Sky Cinema",
        "logo": "https://cdn.jsdelivr.net/gh/HelloPeopleTv4you/tv-logo@refs/heads/main/crichd2-runded/skycinema.png",
        "url": "https://pol7.dunyapurkaraja.com:999/hls/skysme.m3u8?md5=VV2e1LMu21yGT-05v_wTgA&expires=1745054031",
        "referer": "https://stylisheleg4nt.com",
        "origin": "https://stylisheleg4nt.com"
    },
    {
        "name": "Sky Sports Action",
        "logo": "https://cdn.jsdelivr.net/gh/HelloPeopleTv4you/tv-logo@refs/heads/main/crichd2-runded/1745007829332.png",
        "url": "https://pol7.dunyapurkaraja.com:999/hls/skysact.m3u8?md5=JmOR4NkeEN7_89GbIRaWPg&expires=1745054031",
        "referer": "https://stylisheleg4nt.com",
        "origin": "https://stylisheleg4nt.com"
    },
    {
        "name": "Sky Sports Golf",
        "logo": "https://cdn.jsdelivr.net/gh/HelloPeopleTv4you/tv-logo@refs/heads/main/crichd2-runded/1745008055327.png",
        "url": "https://pol5.dunyapurkaraja.com:999/hls/skysgol.m3u8?md5=QG9XwWB7NdzHEixBsKKjjw&expires=1745054031",
        "referer": "https://stylisheleg4nt.com",
        "origin": "https://stylisheleg4nt.com"
    },
    {
        "name": "Sky Sports Premier League",
        "logo": "https://cdn.jsdelivr.net/gh/HelloPeopleTv4you/tv-logo@refs/heads/main/crichd2-runded/43-by-xfireflix.png",
        "url": "https://pol7.dunyapurkaraja.com:999/hls/skysprem.m3u8?md5=96cB2m5GfpYpvhM8dvRgBQ&expires=1745054031",
        "referer": "https://stylisheleg4nt.com",
        "origin": "https://stylisheleg4nt.com"
    },
    {
        "name": "Sky Sports Football",
        "logo": "https://cdn.jsdelivr.net/gh/HelloPeopleTv4you/tv-logo@refs/heads/main/crichd2-runded/44-by-xfireflix.png",
        "url": "https://pol6.dunyapurkaraja.com:999/hls/skysfott.m3u8?md5=Ohsf7F-QKjisFKtqF-LOUw&expires=1745054031",
        "referer": "https://stylisheleg4nt.com",
        "origin": "https://stylisheleg4nt.com"
    },
    {
        "name": "Sky Sports Plus",
        "logo": "https://cdn.jsdelivr.net/gh/HelloPeopleTv4you/tv-logo@refs/heads/main/crichd2-runded/1745008347584.png",
        "url": "https://pol5.dunyapurkaraja.com:999/hls/skysare.m3u8?md5=1lAy-ekgaIJMbFfbPNaMAw&expires=1745054031",
        "referer": "https://stylisheleg4nt.com",
        "origin": "https://stylisheleg4nt.com"
    },
    {
        "name": "Sky Sports F1",
        "logo": "https://cdn.jsdelivr.net/gh/HelloPeopleTv4you/tv-logo@refs/heads/main/crichd2-runded/1745008468637.png",
        "url": "https://pol6.dunyapurkaraja.com:999/hls/skysfor1.m3u8?md5=QNS2gVddDkb2f4uJq5pgkA&expires=1745054031",
        "referer": "https://stylisheleg4nt.com",
        "origin": "https://stylisheleg4nt.com"
    },
    {
        "name": "LaLiGA",
        "logo": "https://cdn.jsdelivr.net/gh/HelloPeopleTv4you/tv-logo@refs/heads/main/crichd2-runded/19-by-xfireflix.png",
        "url": "https://pol6.dunyapurkaraja.com:999/hls/laligauk.m3u8?md5=lDDHRtax7nIcki6bD_TFkA&expires=1745054031",
        "referer": "https://stylisheleg4nt.com",
        "origin": "https://stylisheleg4nt.com"
    },
    {
        "name": "Premier Sports 1",
        "logo": "https://cdn.jsdelivr.net/gh/HelloPeopleTv4you/tv-logo@refs/heads/main/crichd2-runded/31-by-xfireflix.png",
        "url": "https://pol6.dunyapurkaraja.com:999/hls/premieruk.m3u8?md5=_3w29QR61QYk5Z9fCcNTmA&expires=1745054031",
        "referer": "https://stylisheleg4nt.com",
        "origin": "https://stylisheleg4nt.com"
    },
    {
        "name": "Premier Sports 2",
        "logo": "https://cdn.jsdelivr.net/gh/HelloPeopleTv4you/tv-logo@refs/heads/main/crichd2-runded/31-by-xfireflix.png",
        "url": "https://pol6.dunyapurkaraja.com:999/hls/hdchnl2.m3u8?md5=CsV4W96_PUhf27YmSiKYtw&expires=1745054032",
        "referer": "https://stylisheleg4nt.com",
        "origin": "https://stylisheleg4nt.com"
    },
    {
        "name": "Super Football",
        "logo": "https://cdn.jsdelivr.net/gh/HelloPeopleTv4you/tv-logo@refs/heads/main/crichd2-runded/34-by-xfireflix.png",
        "url": "https://pol6.dunyapurkaraja.com:999/hls/superfotball.m3u8?md5=QOKx9jK-y6x23x5cKKFP4A&expires=1745054032",
        "referer": "https://stylisheleg4nt.com",
        "origin": "https://stylisheleg4nt.com"
    },
    {
        "name": "Super Premier League",
        "logo": "https://cdn.jsdelivr.net/gh/HelloPeopleTv4you/tv-logo@refs/heads/main/crichd2-runded/1745008781606.png",
        "url": "https://pol7.dunyapurkaraja.com:999/hls/superpremier.m3u8?md5=UDotlUeXPG6CxVSPO1ebTQ&expires=1745054032",
        "referer": "https://stylisheleg4nt.com",
        "origin": "https://stylisheleg4nt.com"
    },
    {
        "name": "Astro Cricket",
        "logo": "https://cdn.jsdelivr.net/gh/HelloPeopleTv4you/tv-logo@refs/heads/main/crichd2-runded/1745008895589.png",
        "url": "https://pol6.dunyapurkaraja.com:999/hls/fox501.m3u8?md5=SFYgLDUhtCJ6L8Kub2aSEw&expires=1745054032",
        "referer": "https://stylisheleg4nt.com",
        "origin": "https://stylisheleg4nt.com"
    },
    {
        "name": "ESPN 1",
        "logo": "https://cdn.jsdelivr.net/gh/HelloPeopleTv4you/tv-logo@refs/heads/main/crichd2-runded/17-by-xfireflix.png",
        "url": "https://pol5.dunyapurkaraja.com:999/hls/espnusa.m3u8?md5=-Kuc_EBnXxUw5Bwr4gNrgw&expires=1745054032",
        "referer": "https://stylisheleg4nt.com",
        "origin": "https://stylisheleg4nt.com"
    },
    {
        "name": "ESPN 2",
        "logo": "https://cdn.jsdelivr.net/gh/HelloPeopleTv4you/tv-logo@refs/heads/main/crichd2-runded/17-by-xfireflix.png",
        "url": "https://pol7.dunyapurkaraja.com:999/hls/espn2.m3u8?md5=Ea6HeGuZHYFWBzHyVrO0jg&expires=1745054032",
        "referer": "https://stylisheleg4nt.com",
        "origin": "https://stylisheleg4nt.com"
    },
    {
        "name": "Sky Sports Arena",
        "logo": "https://cdn.jsdelivr.net/gh/HelloPeopleTv4you/tv-logo@refs/heads/main/crichd2-runded/1745007829327.png",
        "url": "https://pol5.dunyapurkaraja.com:999/hls/skysare.m3u8?md5=1S1w7EvdT8FZDWMRljUM2g&expires=1745054032",
        "referer": "https://stylisheleg4nt.com",
        "origin": "https://stylisheleg4nt.com"
    },
    {
        "name": "Sky Sports Mix",
        "logo": "https://cdn.jsdelivr.net/gh/HelloPeopleTv4you/tv-logo@refs/heads/main/crichd2-runded/13-by-xfireflix.png",
        "url": "https://pol5.dunyapurkaraja.com:999/hls/skysmixx.m3u8?md5=8TowDjRrAjfUSN4d0s1j5g&expires=1745054032",
        "referer": "https://stylisheleg4nt.com",
        "origin": "https://stylisheleg4nt.com"
    },
    {
        "name": "Sky Sports Tennis",
        "logo": "https://cdn.jsdelivr.net/gh/HelloPeopleTv4you/tv-logo@refs/heads/main/crichd2-runded/1745009085794.png",
        "url": "https://pol5.dunyapurkaraja.com:999/hls/skystennis.m3u8?md5=Z6qaGY4dz9uVVEUHyTfaEg&expires=1745054032",
        "referer": "https://stylisheleg4nt.com",
        "origin": "https://stylisheleg4nt.com"
    },
    {
        "name": "Fox Cricket 501 HD",
        "logo": "https://cdn.jsdelivr.net/gh/HelloPeopleTv4you/tv-logo@refs/heads/main/crichd2-runded/55-by-xfireflix.png",
        "url": "https://pol7.dunyapurkaraja.com:999/hls/fox501.m3u8?md5=SFYgLDUhtCJ6L8Kub2aSEw&expires=1745054032",
        "referer": "https://stylisheleg4nt.com",
        "origin": "https://stylisheleg4nt.com"
    }
]