[
    {
        "name": "Star Sports 1",
        "logo": "https://cdn.jsdelivr.net/gh/HelloPeopleTv4you/tv-logo@refs/heads/main/crichd2-runded/16-by-xfireflix.png",
        "url": "https://pol7.dunyapurkaraja.com:999/hls/star1in.m3u8?md5=JE4i6oicyyAF_Zlo9_kplA&expires=1745453752",
        "referer": "https://stylisheleg4nt.com",
        "origin": "https://stylisheleg4nt.com"
    },
    {
        "name": "Star Sports 1 Hindi",
        "logo": "https://cdn.jsdelivr.net/gh/HelloPeopleTv4you/tv-logo@refs/heads/main/crichd2-runded/1-by-xfireflix.png",
        "url": "https://pol7.dunyapurkaraja.com:999/hls/starhindi.m3u8?md5=GcNp80rUwB9GcdqeeYc3fg&expires=1745453752",
        "referer": "https://stylisheleg4nt.com",
        "origin": "https://stylisheleg4nt.com"
    },
    {
        "name": "PTV Sports",
        "logo": "https://cdn.jsdelivr.net/gh/HelloPeopleTv4you/tv-logo@refs/heads/main/crichd2-runded/20-by-xfireflix.png",
        "url": "https://pol5.dunyapurkaraja.com:999/hls/ptvpk.m3u8?md5=Qmb4OE9mjCFd5ThdTyZM6w&expires=1745453752",
        "referer": "https://stylisheleg4nt.com",
        "origin": "https://stylisheleg4nt.com"
    },
    {
        "name": "Willow HD",
        "logo": "https://cdn.jsdelivr.net/gh/HelloPeopleTv4you/tv-logo@refs/heads/main/crichd2-runded/38-by-xfireflix.png",
        "url": "https://pol7.dunyapurkaraja.com:999/hls/willowusa.m3u8?md5=25ABT0iMO-3PFY6Uam8VDA&expires=1745453753",
        "referer": "https://stylisheleg4nt.com",
        "origin": "https://stylisheleg4nt.com"
    },
    {
        "name": "Willow HD 2",
        "logo": "https://cdn.jsdelivr.net/gh/HelloPeopleTv4you/tv-logo@refs/heads/main/crichd2-runded/8-by-xfireflix.png",
        "url": "https://pol6.dunyapurkaraja.com:999/hls/willowextra.m3u8?md5=DTqt1VOFTWuopyHIkDqNAQ&expires=1745453753",
        "referer": "https://stylisheleg4nt.com",
        "origin": "https://stylisheleg4nt.com"
    },
    {
        "name": "Ten Sports",
        "logo": "https://cdn.jsdelivr.net/gh/HelloPeopleTv4you/tv-logo@refs/heads/main/crichd2-runded/10-by-xfireflix.png",
        "url": "https://pol7.dunyapurkaraja.com:999/hls/tenspk.m3u8?md5=yCXlb9wGmawxbFXB1ehvvw&expires=1745453753",
        "referer": "https://stylisheleg4nt.com",
        "origin": "https://stylisheleg4nt.com"
    },
    {
        "name": "A Sports HD",
        "logo": "https://cdn.jsdelivr.net/gh/HelloPeopleTv4you/tv-logo@refs/heads/main/crichd2-runded/12-by-xfireflix.png",
        "url": "https://pol6.dunyapurkaraja.com:999/hls/asportshd.m3u8?md5=mtDetrsSUjVknI9FDED3Iw&expires=1745453753",
        "referer": "https://stylisheleg4nt.com",
        "origin": "https://stylisheleg4nt.com"
    },
    {
        "name": "Sky Sports Cricket",
        "logo": "https://cdn.jsdelivr.net/gh/HelloPeopleTv4you/tv-logo@refs/heads/main/crichd2-runded/9-by-xfireflix.png",
        "url": "https://pol7.dunyapurkaraja.com:999/hls/skyscric.m3u8?md5=k_5Jew57qYJ6CZkaZklI8g&expires=1745453753",
        "referer": "https://stylisheleg4nt.com",
        "origin": "https://stylisheleg4nt.com"
    },
    {
        "name": "Sky Sports Main Event",
        "logo": "https://cdn.jsdelivr.net/gh/HelloPeopleTv4you/tv-logo@refs/heads/main/crichd2-runded/18-by-xfireflix.png",
        "url": "https://pol5.dunyapurkaraja.com:999/hls/skysme.m3u8?md5=5fXWF2ex8B3z01WcwXq3Aw&expires=1745453753",
        "referer": "https://stylisheleg4nt.com",
        "origin": "https://stylisheleg4nt.com"
    },
    {
        "name": "TNT 1",
        "logo": "https://cdn.jsdelivr.net/gh/HelloPeopleTv4you/tv-logo@refs/heads/main/crichd2-runded/tnt.png",
        "url": "https://pol6.dunyapurkaraja.com:999/hls/bbtsp1.m3u8?md5=xqp01YnLSVJ2Sa2GP1_Mow&expires=1745453754",
        "referer": "https://stylisheleg4nt.com",
        "origin": "https://stylisheleg4nt.com"
    },
    {
        "name": "TNT 2",
        "logo": "https://cdn.jsdelivr.net/gh/HelloPeopleTv4you/tv-logo@refs/heads/main/crichd2-runded/tnt.png",
        "url": "https://pol7.dunyapurkaraja.com:999/hls/bbtsp2.m3u8?md5=sMswWr2DanVuLL3Uyj5EdA&expires=1745453754",
        "referer": "https://stylisheleg4nt.com",
        "origin": "https://stylisheleg4nt.com"
    },
    {
        "name": "TNT 3",
        "logo": "https://cdn.jsdelivr.net/gh/HelloPeopleTv4you/tv-logo@refs/heads/main/crichd2-runded/tnt.png",
        "error": "Token not found or failed to fetch."
    },
    {
        "name": "TNT 4",
        "logo": "https://cdn.jsdelivr.net/gh/HelloPeopleTv4you/tv-logo@refs/heads/main/crichd2-runded/tnt.png",
        "url": "https://pol5.dunyapurkaraja.com:999/hls/bbtespn.m3u8?md5=eMMfG1POIa-Pk32xGKIZQQ&expires=1745453754",
        "referer": "https://stylisheleg4nt.com",
        "origin": "https://stylisheleg4nt.com"
    },
    {
        "name": "Sky Sports 1",
        "logo": "https://cdn.jsdelivr.net/gh/HelloPeopleTv4you/tv-logo@refs/heads/main/crichd2-runded/56-by-xfireflix.png",
        "url": "https://pol6.dunyapurkaraja.com:999/hls/sky1nz.m3u8?md5=rlYy8DE8LeMoCCj9t8_IxQ&expires=1745453754",
        "referer": "https://stylisheleg4nt.com",
        "origin": "https://stylisheleg4nt.com"
    },
    {
        "name": "Sky Sports 2",
        "logo": "https://cdn.jsdelivr.net/gh/HelloPeopleTv4you/tv-logo@refs/heads/main/crichd2-runded/56-by-xfireflix.png",
        "url": "https://pol7.dunyapurkaraja.com:999/hls/sky2nz.m3u8?md5=P4uaVyezhVh1Sp3om8VxeQ&expires=1745453755",
        "referer": "https://stylisheleg4nt.com",
        "origin": "https://stylisheleg4nt.com"
    },
    {
        "name": "Sky Sports 3",
        "logo": "https://cdn.jsdelivr.net/gh/HelloPeopleTv4you/tv-logo@refs/heads/main/crichd2-runded/56-by-xfireflix.png",
        "url": "https://pol7.dunyapurkaraja.com:999/hls/sky3nz.m3u8?md5=xNTtNpUNGAt4hPU7RDfIpg&expires=1745453755",
        "referer": "https://stylisheleg4nt.com",
        "origin": "https://stylisheleg4nt.com"
    },
    {
        "name": "Sky Sports 4",
        "logo": "https://cdn.jsdelivr.net/gh/HelloPeopleTv4you/tv-logo@refs/heads/main/crichd2-runded/56-by-xfireflix.png",
        "url": "https://pol5.dunyapurkaraja.com:999/hls/sky4nz.m3u8?md5=UtZ_C34Eay2w0FkSTNj1QA&expires=1745453755",
        "referer": "https://stylisheleg4nt.com",
        "origin": "https://stylisheleg4nt.com"
    },
    {
        "name": "Sky Sports 5",
        "logo": "https://cdn.jsdelivr.net/gh/HelloPeopleTv4you/tv-logo@refs/heads/main/crichd2-runded/56-by-xfireflix.png",
        "url": "https://pol6.dunyapurkaraja.com:999/hls/sky5nz.m3u8?md5=-GfH1Mjihy7LZPUsguUV7w&expires=1745453755",
        "referer": "https://stylisheleg4nt.com",
        "origin": "https://stylisheleg4nt.com"
    },
    {
        "name": "Sky Sports 6",
        "logo": "https://cdn.jsdelivr.net/gh/HelloPeopleTv4you/tv-logo@refs/heads/main/crichd2-runded/56-by-xfireflix.png",
        "url": "https://pol7.dunyapurkaraja.com:999/hls/sky6nz.m3u8?md5=tg12AdLyTCTBJR75tjO56g&expires=1745453756",
        "referer": "https://stylisheleg4nt.com",
        "origin": "https://stylisheleg4nt.com"
    },
    {
        "name": "Sky Sports 7",
        "logo": "https://cdn.jsdelivr.net/gh/HelloPeopleTv4you/tv-logo@refs/heads/main/crichd2-runded/56-by-xfireflix.png",
        "url": "https://pol6.dunyapurkaraja.com:999/hls/sky7nz.m3u8?md5=4loSZwHWADhWrQA_u8oDWg&expires=1745453756",
        "referer": "https://stylisheleg4nt.com",
        "origin": "https://stylisheleg4nt.com"
    },
    {
        "name": "Sky Sports 8",
        "logo": "https://cdn.jsdelivr.net/gh/HelloPeopleTv4you/tv-logo@refs/heads/main/crichd2-runded/56-by-xfireflix.png",
        "url": "https://pol6.dunyapurkaraja.com:999/hls/sky8nz.m3u8?md5=yigOC1c9vhedWFVWCoe_5A&expires=1745453756",
        "referer": "https://stylisheleg4nt.com",
        "origin": "https://stylisheleg4nt.com"
    },
    {
        "name": "Sky Sports 9",
        "logo": "https://cdn.jsdelivr.net/gh/HelloPeopleTv4you/tv-logo@refs/heads/main/crichd2-runded/56-by-xfireflix.png",
        "url": "https://pol7.dunyapurkaraja.com:999/hls/sky9nz.m3u8?md5=6Ll9Do9ygyOH3fWjAsIDcQ&expires=1745453756",
        "referer": "https://stylisheleg4nt.com",
        "origin": "https://stylisheleg4nt.com"
    },
    {
        "name": "Sky Cinema",
        "logo": "https://cdn.jsdelivr.net/gh/HelloPeopleTv4you/tv-logo@refs/heads/main/crichd2-runded/skycinema.png",
        "url": "https://pol5.dunyapurkaraja.com:999/hls/skysme.m3u8?md5=HbtdeDxS9dO0JCmUnbeEMg&expires=1745453757",
        "referer": "https://stylisheleg4nt.com",
        "origin": "https://stylisheleg4nt.com"
    },
    {
        "name": "Sky Sports Action",
        "logo": "https://cdn.jsdelivr.net/gh/HelloPeopleTv4you/tv-logo@refs/heads/main/crichd2-runded/1745007829332.png",
        "url": "https://pol7.dunyapurkaraja.com:999/hls/skysact.m3u8?md5=TcKs06Z2GKTtRF9WMGuOPg&expires=1745453757",
        "referer": "https://stylisheleg4nt.com",
        "origin": "https://stylisheleg4nt.com"
    },
    {
        "name": "Sky Sports Golf",
        "logo": "https://cdn.jsdelivr.net/gh/HelloPeopleTv4you/tv-logo@refs/heads/main/crichd2-runded/1745008055327.png",
        "url": "https://pol6.dunyapurkaraja.com:999/hls/skysgol.m3u8?md5=eSK9Wkwv1Ph3w4eBK5exCw&expires=1745453757",
        "referer": "https://stylisheleg4nt.com",
        "origin": "https://stylisheleg4nt.com"
    },
    {
        "name": "Sky Sports Premier League",
        "logo": "https://cdn.jsdelivr.net/gh/HelloPeopleTv4you/tv-logo@refs/heads/main/crichd2-runded/43-by-xfireflix.png",
        "error": "Token not found or failed to fetch."
    },
    {
        "name": "Sky Sports Football",
        "logo": "https://cdn.jsdelivr.net/gh/HelloPeopleTv4you/tv-logo@refs/heads/main/crichd2-runded/44-by-xfireflix.png",
        "url": "https://pol5.dunyapurkaraja.com:999/hls/skysfott.m3u8?md5=NrJtTFilhrN4AJ3LnP_Hdw&expires=1745453757",
        "referer": "https://stylisheleg4nt.com",
        "origin": "https://stylisheleg4nt.com"
    },
    {
        "name": "Sky Sports Plus",
        "logo": "https://cdn.jsdelivr.net/gh/HelloPeopleTv4you/tv-logo@refs/heads/main/crichd2-runded/1745008347584.png",
        "url": "https://pol7.dunyapurkaraja.com:999/hls/skysare.m3u8?md5=g227bjP7KFBvirTIQHp7Uw&expires=1745453757",
        "referer": "https://stylisheleg4nt.com",
        "origin": "https://stylisheleg4nt.com"
    },
    {
        "name": "Sky Sports F1",
        "logo": "https://cdn.jsdelivr.net/gh/HelloPeopleTv4you/tv-logo@refs/heads/main/crichd2-runded/1745008468637.png",
        "url": "https://pol5.dunyapurkaraja.com:999/hls/skysfor1.m3u8?md5=taLZaFXMUgGUl6VPtsdrjg&expires=1745453758",
        "referer": "https://stylisheleg4nt.com",
        "origin": "https://stylisheleg4nt.com"
    },
    {
        "name": "LaLiGA",
        "logo": "https://cdn.jsdelivr.net/gh/HelloPeopleTv4you/tv-logo@refs/heads/main/crichd2-runded/19-by-xfireflix.png",
        "url": "https://pol7.dunyapurkaraja.com:999/hls/laligauk.m3u8?md5=WsRkD0F-n-3pE-ssXYnaDg&expires=1745453758",
        "referer": "https://stylisheleg4nt.com",
        "origin": "https://stylisheleg4nt.com"
    },
    {
        "name": "Premier Sports 1",
        "logo": "https://cdn.jsdelivr.net/gh/HelloPeopleTv4you/tv-logo@refs/heads/main/crichd2-runded/31-by-xfireflix.png",
        "url": "https://pol7.dunyapurkaraja.com:999/hls/premieruk.m3u8?md5=CZ4mkBKN6zbtTRyEHLKOWA&expires=1745453758",
        "referer": "https://stylisheleg4nt.com",
        "origin": "https://stylisheleg4nt.com"
    },
    {
        "name": "Premier Sports 2",
        "logo": "https://cdn.jsdelivr.net/gh/HelloPeopleTv4you/tv-logo@refs/heads/main/crichd2-runded/31-by-xfireflix.png",
        "url": "https://pol6.dunyapurkaraja.com:999/hls/hdchnl2.m3u8?md5=C6FSExqYsNHiIexlr4yLqQ&expires=1745453758",
        "referer": "https://stylisheleg4nt.com",
        "origin": "https://stylisheleg4nt.com"
    },
    {
        "name": "Super Football",
        "logo": "https://cdn.jsdelivr.net/gh/HelloPeopleTv4you/tv-logo@refs/heads/main/crichd2-runded/34-by-xfireflix.png",
        "url": "https://pol5.dunyapurkaraja.com:999/hls/superfotball.m3u8?md5=Htp_l2a6bfqBHIgswde36Q&expires=1745453758",
        "referer": "https://stylisheleg4nt.com",
        "origin": "https://stylisheleg4nt.com"
    },
    {
        "name": "Super Premier League",
        "logo": "https://cdn.jsdelivr.net/gh/HelloPeopleTv4you/tv-logo@refs/heads/main/crichd2-runded/1745008781606.png",
        "url": "https://pol7.dunyapurkaraja.com:999/hls/superpremier.m3u8?md5=Zlra1OfDcn39Uhe2bK_7QQ&expires=1745453759",
        "referer": "https://stylisheleg4nt.com",
        "origin": "https://stylisheleg4nt.com"
    },
    {
        "name": "Astro Cricket",
        "logo": "https://cdn.jsdelivr.net/gh/HelloPeopleTv4you/tv-logo@refs/heads/main/crichd2-runded/1745008895589.png",
        "url": "https://pol5.dunyapurkaraja.com:999/hls/fox501.m3u8?md5=5zYuGweUnZtI_SLIuVeq7A&expires=1745453759",
        "referer": "https://stylisheleg4nt.com",
        "origin": "https://stylisheleg4nt.com"
    },
    {
        "name": "ESPN 1",
        "logo": "https://cdn.jsdelivr.net/gh/HelloPeopleTv4you/tv-logo@refs/heads/main/crichd2-runded/17-by-xfireflix.png",
        "error": "Token not found or failed to fetch."
    },
    {
        "name": "ESPN 2",
        "logo": "https://cdn.jsdelivr.net/gh/HelloPeopleTv4you/tv-logo@refs/heads/main/crichd2-runded/17-by-xfireflix.png",
        "url": "https://pol5.dunyapurkaraja.com:999/hls/espn2.m3u8?md5=395nSqRK1mwCIKfcppjiNg&expires=1745453759",
        "referer": "https://stylisheleg4nt.com",
        "origin": "https://stylisheleg4nt.com"
    },
    {
        "name": "Sky Sports Arena",
        "logo": "https://cdn.jsdelivr.net/gh/HelloPeopleTv4you/tv-logo@refs/heads/main/crichd2-runded/1745007829327.png",
        "url": "https://pol5.dunyapurkaraja.com:999/hls/skysare.m3u8?md5=qox-D8HIBOEt17vGzQ8ZKw&expires=1745453759",
        "referer": "https://stylisheleg4nt.com",
        "origin": "https://stylisheleg4nt.com"
    },
    {
        "name": "Sky Sports Mix",
        "logo": "https://cdn.jsdelivr.net/gh/HelloPeopleTv4you/tv-logo@refs/heads/main/crichd2-runded/13-by-xfireflix.png",
        "url": "https://pol6.dunyapurkaraja.com:999/hls/skysmixx.m3u8?md5=0SexgW-GEich_QhJD4fI2Q&expires=1745453760",
        "referer": "https://stylisheleg4nt.com",
        "origin": "https://stylisheleg4nt.com"
    },
    {
        "name": "Sky Sports Tennis",
        "logo": "https://cdn.jsdelivr.net/gh/HelloPeopleTv4you/tv-logo@refs/heads/main/crichd2-runded/1745009085794.png",
        "url": "https://pol7.dunyapurkaraja.com:999/hls/skystennis.m3u8?md5=oFalznCF_ti_sh6oGzJGzA&expires=1745453760",
        "referer": "https://stylisheleg4nt.com",
        "origin": "https://stylisheleg4nt.com"
    },
    {
        "name": "Fox Cricket 501 HD",
        "logo": "https://cdn.jsdelivr.net/gh/HelloPeopleTv4you/tv-logo@refs/heads/main/crichd2-runded/55-by-xfireflix.png",
        "url": "https://pol5.dunyapurkaraja.com:999/hls/fox501.m3u8?md5=oHbGPiqaxXYR5M58TkObbQ&expires=1745453760",
        "referer": "https://stylisheleg4nt.com",
        "origin": "https://stylisheleg4nt.com"
    }
]