[
    {
        "name": "Star Sports 1",
        "logo": "https://cdn.jsdelivr.net/gh/HelloPeopleTv4you/tv-logo@refs/heads/main/crichd2-runded/16-by-xfireflix.png",
        "url": "https://pol7.dunyapurkaraja.com:999/hls/star1in.m3u8?md5=lDCCZihoa8xvfU_EGvjsUg&expires=1745435662",
        "referer": "https://stylisheleg4nt.com",
        "origin": "https://stylisheleg4nt.com"
    },
    {
        "name": "Star Sports 1 Hindi",
        "logo": "https://cdn.jsdelivr.net/gh/HelloPeopleTv4you/tv-logo@refs/heads/main/crichd2-runded/1-by-xfireflix.png",
        "url": "https://pol5.dunyapurkaraja.com:999/hls/starhindi.m3u8?md5=IQeHp7ePTOXmTdJyD8dJaw&expires=1745435663",
        "referer": "https://stylisheleg4nt.com",
        "origin": "https://stylisheleg4nt.com"
    },
    {
        "name": "PTV Sports",
        "logo": "https://cdn.jsdelivr.net/gh/HelloPeopleTv4you/tv-logo@refs/heads/main/crichd2-runded/20-by-xfireflix.png",
        "url": "https://pol6.dunyapurkaraja.com:999/hls/ptvpk.m3u8?md5=6aTUxktlRHV245zdMIvQNQ&expires=1745435663",
        "referer": "https://stylisheleg4nt.com",
        "origin": "https://stylisheleg4nt.com"
    },
    {
        "name": "Willow HD",
        "logo": "https://cdn.jsdelivr.net/gh/HelloPeopleTv4you/tv-logo@refs/heads/main/crichd2-runded/38-by-xfireflix.png",
        "url": "https://pol5.dunyapurkaraja.com:999/hls/willowusa.m3u8?md5=f4M3akSfzdV4vonEiOYurw&expires=1745435663",
        "referer": "https://stylisheleg4nt.com",
        "origin": "https://stylisheleg4nt.com"
    },
    {
        "name": "Willow HD 2",
        "logo": "https://cdn.jsdelivr.net/gh/HelloPeopleTv4you/tv-logo@refs/heads/main/crichd2-runded/8-by-xfireflix.png",
        "url": "https://pol6.dunyapurkaraja.com:999/hls/willowextra.m3u8?md5=-dlupmhca3YCaQKJFw2s2Q&expires=1745435663",
        "referer": "https://stylisheleg4nt.com",
        "origin": "https://stylisheleg4nt.com"
    },
    {
        "name": "Ten Sports",
        "logo": "https://cdn.jsdelivr.net/gh/HelloPeopleTv4you/tv-logo@refs/heads/main/crichd2-runded/10-by-xfireflix.png",
        "url": "https://pol6.dunyapurkaraja.com:999/hls/tenspk.m3u8?md5=UxGn8bOQvudJKBWGW8XAAA&expires=1745435663",
        "referer": "https://stylisheleg4nt.com",
        "origin": "https://stylisheleg4nt.com"
    },
    {
        "name": "A Sports HD",
        "logo": "https://cdn.jsdelivr.net/gh/HelloPeopleTv4you/tv-logo@refs/heads/main/crichd2-runded/12-by-xfireflix.png",
        "url": "https://pol7.dunyapurkaraja.com:999/hls/asportshd.m3u8?md5=Dtl53sd1TZxtB0SoQcoK9w&expires=1745435664",
        "referer": "https://stylisheleg4nt.com",
        "origin": "https://stylisheleg4nt.com"
    },
    {
        "name": "Sky Sports Cricket",
        "logo": "https://cdn.jsdelivr.net/gh/HelloPeopleTv4you/tv-logo@refs/heads/main/crichd2-runded/9-by-xfireflix.png",
        "url": "https://pol5.dunyapurkaraja.com:999/hls/skyscric.m3u8?md5=BpMuxbe4OkK2oIjGmCu_Jg&expires=1745435664",
        "referer": "https://stylisheleg4nt.com",
        "origin": "https://stylisheleg4nt.com"
    },
    {
        "name": "Sky Sports Main Event",
        "logo": "https://cdn.jsdelivr.net/gh/HelloPeopleTv4you/tv-logo@refs/heads/main/crichd2-runded/18-by-xfireflix.png",
        "url": "https://pol7.dunyapurkaraja.com:999/hls/skysme.m3u8?md5=b_jb3o9i-56GaJiBIbmyXw&expires=1745435665",
        "referer": "https://stylisheleg4nt.com",
        "origin": "https://stylisheleg4nt.com"
    },
    {
        "name": "TNT 1",
        "logo": "https://cdn.jsdelivr.net/gh/HelloPeopleTv4you/tv-logo@refs/heads/main/crichd2-runded/tnt.png",
        "url": "https://pol5.dunyapurkaraja.com:999/hls/bbtsp1.m3u8?md5=Gu8JX9IiUdgRSXAK9e6LYw&expires=1745435665",
        "referer": "https://stylisheleg4nt.com",
        "origin": "https://stylisheleg4nt.com"
    },
    {
        "name": "TNT 2",
        "logo": "https://cdn.jsdelivr.net/gh/HelloPeopleTv4you/tv-logo@refs/heads/main/crichd2-runded/tnt.png",
        "url": "https://pol7.dunyapurkaraja.com:999/hls/bbtsp2.m3u8?md5=4oAs4Gdb59N9MF2B9tifqg&expires=1745435665",
        "referer": "https://stylisheleg4nt.com",
        "origin": "https://stylisheleg4nt.com"
    },
    {
        "name": "TNT 3",
        "logo": "https://cdn.jsdelivr.net/gh/HelloPeopleTv4you/tv-logo@refs/heads/main/crichd2-runded/tnt.png",
        "error": "Token not found or failed to fetch."
    },
    {
        "name": "TNT 4",
        "logo": "https://cdn.jsdelivr.net/gh/HelloPeopleTv4you/tv-logo@refs/heads/main/crichd2-runded/tnt.png",
        "url": "https://pol7.dunyapurkaraja.com:999/hls/bbtespn.m3u8?md5=-8tfOfpkG1nCtdjL1chbfg&expires=1745435665",
        "referer": "https://stylisheleg4nt.com",
        "origin": "https://stylisheleg4nt.com"
    },
    {
        "name": "Sky Sports 1",
        "logo": "https://cdn.jsdelivr.net/gh/HelloPeopleTv4you/tv-logo@refs/heads/main/crichd2-runded/56-by-xfireflix.png",
        "url": "https://pol5.dunyapurkaraja.com:999/hls/sky1nz.m3u8?md5=pUuuyGqH3hYp-Fc0sMWamA&expires=1745435665",
        "referer": "https://stylisheleg4nt.com",
        "origin": "https://stylisheleg4nt.com"
    },
    {
        "name": "Sky Sports 2",
        "logo": "https://cdn.jsdelivr.net/gh/HelloPeopleTv4you/tv-logo@refs/heads/main/crichd2-runded/56-by-xfireflix.png",
        "url": "https://pol6.dunyapurkaraja.com:999/hls/sky2nz.m3u8?md5=J4WMLfAsrmDmi6nPfTRanA&expires=1745435666",
        "referer": "https://stylisheleg4nt.com",
        "origin": "https://stylisheleg4nt.com"
    },
    {
        "name": "Sky Sports 3",
        "logo": "https://cdn.jsdelivr.net/gh/HelloPeopleTv4you/tv-logo@refs/heads/main/crichd2-runded/56-by-xfireflix.png",
        "url": "https://pol7.dunyapurkaraja.com:999/hls/sky3nz.m3u8?md5=Wx7QRp0E7LpxjhtqRGz9ew&expires=1745435666",
        "referer": "https://stylisheleg4nt.com",
        "origin": "https://stylisheleg4nt.com"
    },
    {
        "name": "Sky Sports 4",
        "logo": "https://cdn.jsdelivr.net/gh/HelloPeopleTv4you/tv-logo@refs/heads/main/crichd2-runded/56-by-xfireflix.png",
        "url": "https://pol6.dunyapurkaraja.com:999/hls/sky4nz.m3u8?md5=J2YK6ou0QNvqVwB4ghEHaw&expires=1745435667",
        "referer": "https://stylisheleg4nt.com",
        "origin": "https://stylisheleg4nt.com"
    },
    {
        "name": "Sky Sports 5",
        "logo": "https://cdn.jsdelivr.net/gh/HelloPeopleTv4you/tv-logo@refs/heads/main/crichd2-runded/56-by-xfireflix.png",
        "url": "https://pol7.dunyapurkaraja.com:999/hls/sky5nz.m3u8?md5=XlwVMwIdqqXNJHXS3SUXhA&expires=1745435667",
        "referer": "https://stylisheleg4nt.com",
        "origin": "https://stylisheleg4nt.com"
    },
    {
        "name": "Sky Sports 6",
        "logo": "https://cdn.jsdelivr.net/gh/HelloPeopleTv4you/tv-logo@refs/heads/main/crichd2-runded/56-by-xfireflix.png",
        "url": "https://pol5.dunyapurkaraja.com:999/hls/sky6nz.m3u8?md5=KUGKU4P1HJMNmjizBP1zZA&expires=1745435667",
        "referer": "https://stylisheleg4nt.com",
        "origin": "https://stylisheleg4nt.com"
    },
    {
        "name": "Sky Sports 7",
        "logo": "https://cdn.jsdelivr.net/gh/HelloPeopleTv4you/tv-logo@refs/heads/main/crichd2-runded/56-by-xfireflix.png",
        "url": "https://pol5.dunyapurkaraja.com:999/hls/sky7nz.m3u8?md5=yTryPRa-KLRj35pP2bsuog&expires=1745435667",
        "referer": "https://stylisheleg4nt.com",
        "origin": "https://stylisheleg4nt.com"
    },
    {
        "name": "Sky Sports 8",
        "logo": "https://cdn.jsdelivr.net/gh/HelloPeopleTv4you/tv-logo@refs/heads/main/crichd2-runded/56-by-xfireflix.png",
        "url": "https://pol5.dunyapurkaraja.com:999/hls/sky8nz.m3u8?md5=KPPkN0JZE5FdVBhlwbp0bA&expires=1745435668",
        "referer": "https://stylisheleg4nt.com",
        "origin": "https://stylisheleg4nt.com"
    },
    {
        "name": "Sky Sports 9",
        "logo": "https://cdn.jsdelivr.net/gh/HelloPeopleTv4you/tv-logo@refs/heads/main/crichd2-runded/56-by-xfireflix.png",
        "url": "https://pol6.dunyapurkaraja.com:999/hls/sky9nz.m3u8?md5=NS6eSMVGVYGMqCFrPyJrNA&expires=1745435668",
        "referer": "https://stylisheleg4nt.com",
        "origin": "https://stylisheleg4nt.com"
    },
    {
        "name": "Sky Cinema",
        "logo": "https://cdn.jsdelivr.net/gh/HelloPeopleTv4you/tv-logo@refs/heads/main/crichd2-runded/skycinema.png",
        "url": "https://pol6.dunyapurkaraja.com:999/hls/skysme.m3u8?md5=mY5bcEJzu-PFLFtEY5F3Uw&expires=1745435668",
        "referer": "https://stylisheleg4nt.com",
        "origin": "https://stylisheleg4nt.com"
    },
    {
        "name": "Sky Sports Action",
        "logo": "https://cdn.jsdelivr.net/gh/HelloPeopleTv4you/tv-logo@refs/heads/main/crichd2-runded/1745007829332.png",
        "url": "https://pol7.dunyapurkaraja.com:999/hls/skysact.m3u8?md5=gSIu8KY2ozgc9pIKESmXbg&expires=1745435669",
        "referer": "https://stylisheleg4nt.com",
        "origin": "https://stylisheleg4nt.com"
    },
    {
        "name": "Sky Sports Golf",
        "logo": "https://cdn.jsdelivr.net/gh/HelloPeopleTv4you/tv-logo@refs/heads/main/crichd2-runded/1745008055327.png",
        "url": "https://pol7.dunyapurkaraja.com:999/hls/skysgol.m3u8?md5=QFMnkVfV67_npVb4p2Lx5A&expires=1745435669",
        "referer": "https://stylisheleg4nt.com",
        "origin": "https://stylisheleg4nt.com"
    },
    {
        "name": "Sky Sports Premier League",
        "logo": "https://cdn.jsdelivr.net/gh/HelloPeopleTv4you/tv-logo@refs/heads/main/crichd2-runded/43-by-xfireflix.png",
        "url": "https://pol7.dunyapurkaraja.com:999/hls/skysprem.m3u8?md5=ITlxSi8xYf10Gz7zUdpQNQ&expires=1745435669",
        "referer": "https://stylisheleg4nt.com",
        "origin": "https://stylisheleg4nt.com"
    },
    {
        "name": "Sky Sports Football",
        "logo": "https://cdn.jsdelivr.net/gh/HelloPeopleTv4you/tv-logo@refs/heads/main/crichd2-runded/44-by-xfireflix.png",
        "url": "https://pol7.dunyapurkaraja.com:999/hls/skysfott.m3u8?md5=-T-fVHLNqvrQemQvOnDXtg&expires=1745435669",
        "referer": "https://stylisheleg4nt.com",
        "origin": "https://stylisheleg4nt.com"
    },
    {
        "name": "Sky Sports Plus",
        "logo": "https://cdn.jsdelivr.net/gh/HelloPeopleTv4you/tv-logo@refs/heads/main/crichd2-runded/1745008347584.png",
        "url": "https://pol7.dunyapurkaraja.com:999/hls/skysare.m3u8?md5=vN0ORD6p0KqchBdgHPK-6Q&expires=1745435669",
        "referer": "https://stylisheleg4nt.com",
        "origin": "https://stylisheleg4nt.com"
    },
    {
        "name": "Sky Sports F1",
        "logo": "https://cdn.jsdelivr.net/gh/HelloPeopleTv4you/tv-logo@refs/heads/main/crichd2-runded/1745008468637.png",
        "url": "https://pol7.dunyapurkaraja.com:999/hls/skysfor1.m3u8?md5=65NnhUs1VIhsTKpdT_wyQA&expires=1745435670",
        "referer": "https://stylisheleg4nt.com",
        "origin": "https://stylisheleg4nt.com"
    },
    {
        "name": "LaLiGA",
        "logo": "https://cdn.jsdelivr.net/gh/HelloPeopleTv4you/tv-logo@refs/heads/main/crichd2-runded/19-by-xfireflix.png",
        "url": "https://pol5.dunyapurkaraja.com:999/hls/laligauk.m3u8?md5=ZzdjuQkUoPQnhdcyW4922g&expires=1745435670",
        "referer": "https://stylisheleg4nt.com",
        "origin": "https://stylisheleg4nt.com"
    },
    {
        "name": "Premier Sports 1",
        "logo": "https://cdn.jsdelivr.net/gh/HelloPeopleTv4you/tv-logo@refs/heads/main/crichd2-runded/31-by-xfireflix.png",
        "url": "https://pol6.dunyapurkaraja.com:999/hls/premieruk.m3u8?md5=yZyDs3YJ_K83XnYhdXQpkQ&expires=1745435670",
        "referer": "https://stylisheleg4nt.com",
        "origin": "https://stylisheleg4nt.com"
    },
    {
        "name": "Premier Sports 2",
        "logo": "https://cdn.jsdelivr.net/gh/HelloPeopleTv4you/tv-logo@refs/heads/main/crichd2-runded/31-by-xfireflix.png",
        "url": "https://pol7.dunyapurkaraja.com:999/hls/hdchnl2.m3u8?md5=pmNbw5Kq-i9fQ6IUkTpszQ&expires=1745435671",
        "referer": "https://stylisheleg4nt.com",
        "origin": "https://stylisheleg4nt.com"
    },
    {
        "name": "Super Football",
        "logo": "https://cdn.jsdelivr.net/gh/HelloPeopleTv4you/tv-logo@refs/heads/main/crichd2-runded/34-by-xfireflix.png",
        "url": "https://pol5.dunyapurkaraja.com:999/hls/superfotball.m3u8?md5=dn3Cxw882DbXDb6jjTPntQ&expires=1745435671",
        "referer": "https://stylisheleg4nt.com",
        "origin": "https://stylisheleg4nt.com"
    },
    {
        "name": "Super Premier League",
        "logo": "https://cdn.jsdelivr.net/gh/HelloPeopleTv4you/tv-logo@refs/heads/main/crichd2-runded/1745008781606.png",
        "url": "https://pol5.dunyapurkaraja.com:999/hls/superpremier.m3u8?md5=sMuTLpiCkoi8Q8QB5OVCqw&expires=1745435671",
        "referer": "https://stylisheleg4nt.com",
        "origin": "https://stylisheleg4nt.com"
    },
    {
        "name": "Astro Cricket",
        "logo": "https://cdn.jsdelivr.net/gh/HelloPeopleTv4you/tv-logo@refs/heads/main/crichd2-runded/1745008895589.png",
        "url": "https://pol6.dunyapurkaraja.com:999/hls/fox501.m3u8?md5=tmphAVrMKS-342R4nrqJwA&expires=1745435671",
        "referer": "https://stylisheleg4nt.com",
        "origin": "https://stylisheleg4nt.com"
    },
    {
        "name": "ESPN 1",
        "logo": "https://cdn.jsdelivr.net/gh/HelloPeopleTv4you/tv-logo@refs/heads/main/crichd2-runded/17-by-xfireflix.png",
        "url": "https://pol7.dunyapurkaraja.com:999/hls/espnusa.m3u8?md5=aBSEY0fFLh4TCA7HjbAAbA&expires=1745435671",
        "referer": "https://stylisheleg4nt.com",
        "origin": "https://stylisheleg4nt.com"
    },
    {
        "name": "ESPN 2",
        "logo": "https://cdn.jsdelivr.net/gh/HelloPeopleTv4you/tv-logo@refs/heads/main/crichd2-runded/17-by-xfireflix.png",
        "url": "https://pol7.dunyapurkaraja.com:999/hls/espn2.m3u8?md5=oeaP5A7d-cJhAkpvxd63DQ&expires=1745435671",
        "referer": "https://stylisheleg4nt.com",
        "origin": "https://stylisheleg4nt.com"
    },
    {
        "name": "Sky Sports Arena",
        "logo": "https://cdn.jsdelivr.net/gh/HelloPeopleTv4you/tv-logo@refs/heads/main/crichd2-runded/1745007829327.png",
        "url": "https://pol7.dunyapurkaraja.com:999/hls/skysare.m3u8?md5=bfuQqjGP0lPijbxEzFMqXA&expires=1745435671",
        "referer": "https://stylisheleg4nt.com",
        "origin": "https://stylisheleg4nt.com"
    },
    {
        "name": "Sky Sports Mix",
        "logo": "https://cdn.jsdelivr.net/gh/HelloPeopleTv4you/tv-logo@refs/heads/main/crichd2-runded/13-by-xfireflix.png",
        "url": "https://pol5.dunyapurkaraja.com:999/hls/skysmixx.m3u8?md5=_8SsdfmrciI2Y7KfMr1B7w&expires=1745435672",
        "referer": "https://stylisheleg4nt.com",
        "origin": "https://stylisheleg4nt.com"
    },
    {
        "name": "Sky Sports Tennis",
        "logo": "https://cdn.jsdelivr.net/gh/HelloPeopleTv4you/tv-logo@refs/heads/main/crichd2-runded/1745009085794.png",
        "url": "https://pol7.dunyapurkaraja.com:999/hls/skystennis.m3u8?md5=BZeUOwuBaAxmTe82z97T4w&expires=1745435672",
        "referer": "https://stylisheleg4nt.com",
        "origin": "https://stylisheleg4nt.com"
    },
    {
        "name": "Fox Cricket 501 HD",
        "logo": "https://cdn.jsdelivr.net/gh/HelloPeopleTv4you/tv-logo@refs/heads/main/crichd2-runded/55-by-xfireflix.png",
        "url": "https://pol5.dunyapurkaraja.com:999/hls/fox501.m3u8?md5=dVk8s6SjHDKoylp2IQxDuA&expires=1745435672",
        "referer": "https://stylisheleg4nt.com",
        "origin": "https://stylisheleg4nt.com"
    }
]